{
  "source": {
    "name": "goodreads",
    "url": "https://www.goodreads.com/review/show/1021622920?utm_medium=api&utm_source=rss"
  },
  "lang": "en",
  "published": "2014-08-09T14:55:43.000Z",
  "content": "📚 Finished reading <a href=\"https://www.goodreads.com/review/show/1021622920?utm_medium=api&utm_source=rss\" rel=\"nofollow noopener noreferrer\">Einstein's Relativity and the Quantum Revolution: Modern Physics for Non-Scientists</a> by Richard Wolfson",
  "id": "911a4a5bf697fdbbc348b5c3cc99bad0"
}