{
  "source": {
    "name": "vimwiki",
    "url": "https://wiki.bazadanni.com/quotelog/"
  },
  "published": "2021-12-20T04:19:17.000Z",
  "content": "I enjoy development. I just don’t want to work as a developer anymore. It is an analogous situation to that friend of yours who enjoys cooking but doesn’t want to work in a restaurant. <a href=\"https://andregarzia.com/2021/12/the-blog-is-the-program.html\" rel=\"nofollow noopener noreferrer\">The Blog is the program • AndreGarzia.com</a>",
  "id": "4f959eff4b383c2bda7c02c282a45d4b"
}