{
  "source": {
    "name": "spotify",
    "url": "https://open.spotify.com/track/2vrtV6t5SxPKPcTCtlE3wY"
  },
  "lang": "en",
  "published": "2022-05-05T06:10:49.000Z",
  "content": "❤️ 🎶: <a href=\"https://open.spotify.com/track/2vrtV6t5SxPKPcTCtlE3wY\" rel=\"nofollow noopener noreferrer\">Всичко feat. Geri Turiyska</a> by <a href=\"https://open.spotify.com/artist/2Kp8AR8JhspsnKHxmvvABA\" rel=\"nofollow noopener noreferrer\">Rubikub</a>, <a href=\"https://open.spotify.com/artist/2fk1LHIxxde4qkCSTRlOkQ\" rel=\"nofollow noopener noreferrer\">Geri Turiyska</a>",
  "id": "1c76cc734505183d543882b9d2d7f60c"
}